lseg/__init__.py
lseg/data/__init__.py
lseg/data/__init__.pyi
lseg/data/_base_enum.py
lseg/data/_config_defaults.py
lseg/data/_configure.py
lseg/data/_content_type.py
lseg/data/_errors.py
lseg/data/_layer_type.py
lseg/data/_listener.py
lseg/data/_log.py
lseg/data/_open_state.py
lseg/data/_types.py
lseg/data/_version.py
lseg/data/errors.py
lseg/data/warnings.py
lseg/data/_access_layer/__init__.py
lseg/data/_access_layer/_containers.py
lseg/data/_access_layer/_data_df_builder.py
lseg/data/_access_layer/_data_provider.py
lseg/data/_access_layer/_history_df_builder.py
lseg/data/_access_layer/_intervals_consts.py
lseg/data/_access_layer/_mixed_streams.py
lseg/data/_access_layer/_ohlc_builder.py
lseg/data/_access_layer/_pricing_recorder.py
lseg/data/_access_layer/_recording_control.py
lseg/data/_access_layer/_stream_update_handler.py
lseg/data/_access_layer/get_data_func.py
lseg/data/_access_layer/get_history_func.py
lseg/data/_access_layer/get_stream.py
lseg/data/_access_layer/session.py
lseg/data/_access_layer/context_collection/__init__.py
lseg/data/_access_layer/context_collection/_adc_and_cust_inst_context.py
lseg/data/_access_layer/context_collection/_adc_context.py
lseg/data/_access_layer/context_collection/_context.py
lseg/data/_access_layer/context_collection/_context_factory.py
lseg/data/_access_layer/context_collection/_cust_inst_context.py
lseg/data/_access_layer/context_collection/_hp_context.py
lseg/data/_access_layer/dates_and_calendars/__init__.py
lseg/data/_access_layer/dates_and_calendars/_add_periods.py
lseg/data/_access_layer/dates_and_calendars/_count_periods.py
lseg/data/_access_layer/dates_and_calendars/_date_schedule.py
lseg/data/_access_layer/dates_and_calendars/_holidays.py
lseg/data/_access_layer/dates_and_calendars/_is_working_day.py
lseg/data/_access_layer/news/__init__.py
lseg/data/_access_layer/news/_news.py
lseg/data/_access_layer/tradefeedr/__init__.py
lseg/data/_access_layer/tradefeedr/_tradefeedr.py
lseg/data/_adc_headers/__init__.py
lseg_data-2.1.0.dist-info/licenses/LICENSE
lseg_data-2.1.0.dist-info/METADATA
lseg_data-2.1.0.dist-info/WHEEL
lseg_data-2.1.0.dist-info/top_level.txt
lseg_data-2.1.0.dist-info/RECORD
