Metadata-Version: 2.4
Name: lseg-data
Version: 2.1.0
Summary: Client for LSEG Data Platform API's
Author: LSEG
License: Apache 2.0
Project-URL: Homepage, https://developers.lseg.com/en/api-catalog/lseg-data-platform/lseg-data-library-for-python
Project-URL: Documentation, https://developers.lseg.com/en/api-catalog/lseg-data-platform/lseg-data-library-for-python/documentation
Classifier: License :: OSI Approved :: Apache Software License
Classifier: Operating System :: OS Independent
Classifier: Programming Language :: Python :: 3
Classifier: Topic :: Office/Business :: Financial
Requires-Python: >=3.9
License-File: LICENSE
Requires-Dist: appdirs~=1.4.4
Requires-Dist: pyee<=12,>=9.0.4
Requires-Dist: httpx<0.28,>=0.18.0
Requires-Dist: httpcore<1.1.0
Requires-Dist: numpy
Requires-Dist: pandas
Requires-Dist: python-dateutil
Requires-Dist: requests
Requires-Dist: scipy
Requires-Dist: tenacity
Requires-Dist: watchdog
Requires-Dist: websocket-client!=1.5.0,!=1.5.2,>=1.5
Requires-Dist: pyhumps<4.0.0,>=3.0.2
Requires-Dist: jinja2<4.0.0,>=3.0.3
Requires-Dist: simplejson
Dynamic: license-file
